Outliers/outlierRemoval.py
101703311_OUTLIERS-1.0.2.dist-info/LICENSE.txt
101703311_OUTLIERS-1.0.2.dist-info/METADATA
101703311_OUTLIERS-1.0.2.dist-info/WHEEL
101703311_OUTLIERS-1.0.2.dist-info/entry_points.txt
101703311_OUTLIERS-1.0.2.dist-info/top_level.txt
101703311_OUTLIERS-1.0.2.dist-info/RECORD
